miscbox-0.2.0.dist-info/METADATA
miscbox-0.2.0.dist-info/WHEEL
miscbox-0.2.0.dist-info/entry_points.txt
miscbox-0.2.0.dist-info/licenses/LICENSE
miscbox/__init__.py
miscbox/deb_extract.py
miscbox/dir_archive.py
miscbox/enc_recover.py
miscbox/logging.py
miscbox/merge_ip_ranges.py
miscbox/mobi_archive.py
miscbox/net_stats.py
miscbox/pascal.py
miscbox/punc_conv.py
miscbox/rename_with_date.py
miscbox/rotate_images.py
miscbox/shasum_list.py
miscbox/sort_keys.py
miscbox/urlencode.py
miscbox-0.2.0.dist-info/RECORD
